{
	"dialogueNodes":
		[
			{
				"id": 0,
				"spokenWords": "This discarded clay pot may come in handy.",
				"replies": [],
				"nodeLinks": [],
				"speakerName": "medusa",
				"speakerOnePortrait": "medusa_normal_mask",
				"onePortraitFacingDirection": "right",
				"speakerTwoPortrait": "",
				"twoPortraitFacingDirection": "",
				"centerPortrait": "",
				"voice": "female",
				"audioSFX": "",
				"musicCue": "",
				"overrideFacingDirectionPlayer": "",
				"currentNpc": "",
				"overrideFacingDirectionNPC":"",
				"taskCompleted": ""
			}
		]
	
}