{
	"dialogueNodes":
		[
			{
				"id": 0,
				"spokenWords": "If you don't have any money, stop wasting my time.",
				"replies": [],
				"nodeLinks": [1],
				"speakerName": "citizen",
				"speakerOnePortrait": "",
				"onePortraitFacingDirection": "",
				"speakerTwoPortrait": "",
				"twoPortraitFacingDirection": "",
				"centerPortrait": "",
				"voice": "male",
				"audioSFX": "",
				"musicCue": "",
				"overrideFacingDirectionPlayer": "",
				"currentNpc": "",
				"overrideFacingDirectionNPC":"",
				"taskCompleted": ""
			},

			{
				"id": 1,
				"spokenWords": "I only deal with paying customers.",
				"replies": [],
				"nodeLinks": [],
				"speakerName": "citizen",
				"speakerOnePortrait": "",
				"onePortraitFacingDirection": "",
				"speakerTwoPortrait": "",
				"twoPortraitFacingDirection": "",
				"centerPortrait": "",
				"voice": "male",
				"audioSFX": "",
				"musicCue": "",
				"overrideFacingDirectionPlayer": "",
				"currentNpc": "",
				"overrideFacingDirectionNPC":"",
				"taskCompleted": ""
			}
		]
	
}